pyvn/__init__.py
pyvn/ivscript.py
pyvn/jdata.py
pyvn/josen.py
pyvn/run.py
pyvn/yaml.py
pyvn-1.1.dist-info/DESCRIPTION.rst
pyvn-1.1.dist-info/METADATA
pyvn-1.1.dist-info/RECORD
pyvn-1.1.dist-info/WHEEL
pyvn-1.1.dist-info/metadata.json
pyvn-1.1.dist-info/top_level.txt
