Metadata-Version: 2.0
Name: pyvn
Version: 1.1
Summary: Python3 Ivnosys Utils
Home-page: https://ivnosys.com
Author: Ivnosys Soluciones S.L.
Author-email: jbiosca@ivnosys.com
License: UNKNOWN
Platform: UNKNOWN
Classifier: Development Status :: 4 - Beta
Requires-Dist: dicttoxml
Requires-Dist: ruamel.yaml
Requires-Dist: setuptools
Requires-Dist: xmltodict
